[{"id": 115270, "rank": 1, "value": ".368", "league": "NL"}, {"id": 118365, "rank": 2, "value": ".356", "league": "AL"}, {"id": 120536, "rank": 3, "value": ".346", "league": "NL"}, {"id": 110974, "rank": 4, "value": ".340", "league": "NL"}, {"id": 110818, "rank": 5, "value": ".334", "league": "NL"}, {"id": 117197, "rank": 6, "value": ".333", "league": "AL"}, {"id": 121640, "rank": 7, "value": ".330", "league": "AL"}, {"id": 111199, "rank": 8, "value": ".329", "league": "AL"}, {"id": 115007, "rank": 9, "value": ".326", "league": "NL"}, {"id": 111153, "rank": 10, "value": ".324", "league": "AL"}, {"id": 119579, "rank": 11, "value": ".323", "league": "AL"}, {"id": 122989, "rank": 12, "value": ".320", "league": "AL"}, {"id": 117501, "rank": 13, "value": ".319", "league": "NL"}, {"id": 113099, "rank": 14, "value": ".318", "league": "AL"}, {"id": 110839, "rank": 15, "value": ".317", "league": "AL"}, {"id": 110427, "rank": 16, "value": ".314", "league": "AL"}, {"id": 123272, "rank": 17, "value": ".314", "league": "AL"}, {"id": 120790, "rank": 18, "value": ".314", "league": "AL"}, {"id": 121983, "rank": 19, "value": ".311", "league": "AL"}, {"id": 120191, "rank": 20, "value": ".310", "league": "AL"}, {"id": 117863, "rank": 21, "value": ".310", "league": "AL"}, {"id": 116780, "rank": 22, "value": ".310", "league": "AL"}, {"id": 112106, "rank": 23, "value": ".309", "league": "NL"}, {"id": 121977, "rank": 24, "value": ".309", "league": "NL"}, {"id": 123245, "rank": 25, "value": ".308", "league": "AL"}, {"id": 120903, "rank": 26, "value": ".308", "league": "AL"}, {"id": 124288, "rank": 27, "value": ".307", "league": "AL"}, {"id": 119634, "rank": 28, "value": ".307", "league": "AL"}, {"id": 116603, "rank": 29, "value": ".306", "league": "AL"}, {"id": 116513, "rank": 30, "value": ".306", "league": "NL"}]