[{"id": 117863, "rank": 1, "value": "75", "league": "AL"}, {"id": 114961, "rank": 2, "value": "66", "league": "AL"}, {"id": 119812, "rank": 3, "value": "54", "league": "AL"}, {"id": 124695, "rank": 4, "value": "53", "league": "NL"}, {"id": 116603, "rank": 5, "value": "50", "league": "NL"}, {"id": 113291, "rank": 6, "value": "48", "league": "NL"}, {"id": 117197, "rank": 7, "value": "45", "league": "AL"}, {"id": 111188, "rank": 8, "value": "40", "league": "NL"}, {"id": 118329, "rank": 9, "value": "38", "league": "NL"}, {"id": 115749, "rank": 10, "value": "37", "league": "NL"}, {"id": 118871, "rank": 10, "value": "37", "league": "NL"}, {"id": 117501, "rank": 12, "value": "36", "league": "NL"}, {"id": 116326, "rank": 13, "value": "35", "league": "NL"}, {"id": 117484, "rank": 13, "value": "35", "league": "NL"}, {"id": 123744, "rank": 13, "value": "35", "league": "AL"}, {"id": 112381, "rank": 16, "value": "33", "league": "NL"}, {"id": 115210, "rank": 16, "value": "33", "league": "NL"}, {"id": 111736, "rank": 18, "value": "32", "league": "NL"}, {"id": 110974, "rank": 19, "value": "31", "league": "NL"}, {"id": 113660, "rank": 20, "value": "30", "league": "AL"}, {"id": 110818, "rank": 21, "value": "29", "league": "NL"}, {"id": 115174, "rank": 22, "value": "28", "league": "NL"}, {"id": 118808, "rank": 23, "value": "27", "league": "AL"}, {"id": 119347, "rank": 24, "value": "26", "league": "NL"}, {"id": 110214, "rank": 25, "value": "25", "league": "AL"}, {"id": 110847, "rank": 25, "value": "25", "league": "NL"}, {"id": 110987, "rank": 25, "value": "25", "league": "NL"}, {"id": 113028, "rank": 25, "value": "25", "league": "AL"}, {"id": 117815, "rank": 25, "value": "25", "league": "AL"}, {"id": 119948, "rank": 30, "value": "24", "league": "AL"}, {"id": 121673, "rank": 30, "value": "24", "league": "NL"}]