[{"id": 119403, "rank": 1, "value": "22", "league": "NL"}, {"id": 121811, "rank": 1, "value": "22", "league": "NL"}, {"id": 116615, "rank": 3, "value": "21", "league": "NL"}, {"id": 150426, "rank": 3, "value": "21", "league": "AL"}, {"id": 112388, "rank": 5, "value": "20", "league": "AL"}, {"id": 117758, "rank": 5, "value": "20", "league": "NL"}, {"id": 119469, "rank": 5, "value": "20", "league": "AL"}, {"id": 150119, "rank": 8, "value": "18", "league": "AL"}, {"id": 218596, "rank": 8, "value": "18", "league": "AL"}, {"id": 110015, "rank": 10, "value": "17", "league": "AL"}, {"id": 118120, "rank": 10, "value": "17", "league": "NL"}, {"id": 150222, "rank": 10, "value": "17", "league": "AL"}, {"id": 119608, "rank": 10, "value": "17", "league": "AL"}, {"id": 133460, "rank": 10, "value": "17", "league": "NL"}, {"id": 282332, "rank": 10, "value": "17", "league": "AL"}, {"id": 217096, "rank": 10, "value": "17", "league": "AL"}, {"id": 279824, "rank": 17, "value": "16", "league": "AL"}, {"id": 114849, "rank": 17, "value": "16", "league": "NL"}, {"id": 117046, "rank": 17, "value": "16", "league": "NL"}, {"id": 150063, "rank": 17, "value": "16", "league": "NL"}, {"id": 134320, "rank": 17, "value": "16", "league": "NL"}, {"id": 133225, "rank": 22, "value": "15", "league": "NL"}, {"id": 132980, "rank": 22, "value": "15", "league": "AL"}, {"id": 120221, "rank": 22, "value": "15", "league": "NL"}, {"id": 120447, "rank": 22, "value": "15", "league": "NL"}, {"id": 120485, "rank": 22, "value": "15", "league": "AL"}, {"id": 120878, "rank": 22, "value": "15", "league": "AL"}, {"id": 121986, "rank": 22, "value": "15", "league": "AL"}, {"id": 124315, "rank": 22, "value": "15", "league": "NL"}, {"id": 112526, "rank": 30, "value": "14", "league": "AL"}, {"id": 115399, "rank": 30, "value": "14", "league": "NL"}, {"id": 115812, "rank": 30, "value": "14", "league": "NL"}, {"id": 400061, "rank": 30, "value": "14", "league": "NL"}, {"id": 121110, "rank": 30, "value": "14", "league": "NL"}, {"id": 121541, "rank": 30, "value": "14", "league": "NL"}, {"id": 122562, "rank": 30, "value": "14", "league": "AL"}]