[{"id": 408210, "rank": 1, "value": "62", "league": "AL"}, {"id": 408314, "rank": 2, "value": "60", "league": "NL"}, {"id": 325392, "rank": 3, "value": "59", "league": "AL"}, {"id": 334393, "rank": 4, "value": "57", "league": "NL"}, {"id": 408307, "rank": 5, "value": "46", "league": "AL"}, {"id": 279577, "rank": 5, "value": "46", "league": "NL"}, {"id": 276519, "rank": 7, "value": "41", "league": "NL"}, {"id": 150061, "rank": 8, "value": "39", "league": "AL"}, {"id": 150472, "rank": 9, "value": "36", "league": "NL"}, {"id": 430838, "rank": 10, "value": "34", "league": "NL"}, {"id": 400085, "rank": 11, "value": "33", "league": "AL"}, {"id": 110029, "rank": 12, "value": "31", "league": "NL"}, {"id": 150093, "rank": 13, "value": "30", "league": "AL"}, {"id": 406878, "rank": 14, "value": "27", "league": "AL"}, {"id": 124523, "rank": 14, "value": "27", "league": "AL"}, {"id": 112736, "rank": 16, "value": "26", "league": "NL"}, {"id": 123744, "rank": 17, "value": "24", "league": "NL"}, {"id": 116338, "rank": 18, "value": "23", "league": "AL"}, {"id": 425497, "rank": 18, "value": "23", "league": "AL"}, {"id": 150353, "rank": 18, "value": "23", "league": "NL"}, {"id": 117863, "rank": 21, "value": "22", "league": "NL"}, {"id": 429713, "rank": 21, "value": "22", "league": "AL"}, {"id": 424726, "rank": 23, "value": "21", "league": "NL"}, {"id": 111851, "rank": 23, "value": "21", "league": "AL"}, {"id": 276361, "rank": 23, "value": "21", "league": "NL"}, {"id": 121347, "rank": 23, "value": "21", "league": "AL"}, {"id": 431157, "rank": 27, "value": "20", "league": "AL"}, {"id": 150456, "rank": 28, "value": "19", "league": "AL"}, {"id": 133160, "rank": 28, "value": "19", "league": "NL"}, {"id": 113028, "rank": 30, "value": "18", "league": "AL"}, {"id": 407849, "rank": 30, "value": "18", "league": "NL"}, {"id": 117566, "rank": 30, "value": "18", "league": "AL"}]