[{"id": 276371, "rank": 1, "value": "238", "league": "AL"}, {"id": 408241, "rank": 2, "value": "216", "league": "NL"}, {"id": 112020, "rank": 3, "value": "213", "league": "NL"}, {"id": 116615, "rank": 4, "value": "211", "league": "AL"}, {"id": 150277, "rank": 5, "value": "208", "league": "NL"}, {"id": 118377, "rank": 5, "value": "208", "league": "NL"}, {"id": 408206, "rank": 5, "value": "208", "league": "NL"}, {"id": 407296, "rank": 8, "value": "202", "league": "NL"}, {"id": 407793, "rank": 9, "value": "199", "league": "AL"}, {"id": 150359, "rank": 10, "value": "198", "league": "NL"}, {"id": 134320, "rank": 11, "value": "192", "league": "NL"}, {"id": 407578, "rank": 12, "value": "188", "league": "NL"}, {"id": 112388, "rank": 13, "value": "185", "league": "NL"}, {"id": 279568, "rank": 13, "value": "185", "league": "NL"}, {"id": 400061, "rank": 15, "value": "184", "league": "NL"}, {"id": 425626, "rank": 16, "value": "176", "league": "NL"}, {"id": 431148, "rank": 17, "value": "174", "league": "AL"}, {"id": 117842, "rank": 18, "value": "173", "league": "NL"}, {"id": 430161, "rank": 19, "value": "172", "league": "NL"}, {"id": 425630, "rank": 19, "value": "172", "league": "NL"}, {"id": 120485, "rank": 21, "value": "171", "league": "NL"}, {"id": 217096, "rank": 21, "value": "171", "league": "AL"}, {"id": 425883, "rank": 23, "value": "170", "league": "NL"}, {"id": 122477, "rank": 24, "value": "169", "league": "NL"}, {"id": 277417, "rank": 25, "value": "166", "league": "NL"}, {"id": 121834, "rank": 26, "value": "165", "league": "NL"}, {"id": 421685, "rank": 27, "value": "163", "league": "NL"}, {"id": 429717, "rank": 27, "value": "163", "league": "AL"}, {"id": 282332, "rank": 29, "value": "161", "league": "AL"}, {"id": 425555, "rank": 30, "value": "157", "league": "AL"}, {"id": 112526, "rank": 30, "value": "157", "league": "AL"}, {"id": 213711, "rank": 30, "value": "157", "league": "NL"}]