[{"id": 400085, "rank": 1, "value": "224", "league": "AL"}, {"id": 276545, "rank": 2, "value": "217", "league": "AL"}, {"id": 116539, "rank": 3, "value": "214", "league": "AL"}, {"id": 123173, "rank": 3, "value": "214", "league": "AL"}, {"id": 334393, "rank": 5, "value": "204", "league": "NL"}, {"id": 400284, "rank": 6, "value": "203", "league": "NL"}, {"id": 115223, "rank": 7, "value": "200", "league": "AL"}, {"id": 408108, "rank": 7, "value": "200", "league": "NL"}, {"id": 425548, "rank": 9, "value": "198", "league": "NL"}, {"id": 279577, "rank": 10, "value": "196", "league": "NL"}, {"id": 407812, "rank": 10, "value": "196", "league": "NL"}, {"id": 408234, "rank": 12, "value": "195", "league": "NL"}, {"id": 150439, "rank": 13, "value": "194", "league": "AL"}, {"id": 408314, "rank": 13, "value": "194", "league": "NL"}, {"id": 276519, "rank": 15, "value": "191", "league": "NL"}, {"id": 408047, "rank": 16, "value": "190", "league": "AL"}, {"id": 429713, "rank": 16, "value": "190", "league": "AL"}, {"id": 150324, "rank": 18, "value": "187", "league": "AL"}, {"id": 434670, "rank": 19, "value": "185", "league": "NL"}, {"id": 150484, "rank": 19, "value": "185", "league": "AL"}, {"id": 408307, "rank": 21, "value": "183", "league": "AL"}, {"id": 429667, "rank": 22, "value": "182", "league": "NL"}, {"id": 116380, "rank": 23, "value": "181", "league": "AL"}, {"id": 117928, "rank": 23, "value": "181", "league": "AL"}, {"id": 400121, "rank": 23, "value": "181", "league": "AL"}, {"id": 408045, "rank": 23, "value": "181", "league": "AL"}, {"id": 407489, "rank": 23, "value": "181", "league": "AL"}, {"id": 431151, "rank": 23, "value": "181", "league": "NL"}, {"id": 150093, "rank": 29, "value": "179", "league": "NL"}, {"id": 117244, "rank": 30, "value": "177", "league": "AL"}, {"id": 120044, "rank": 30, "value": "177", "league": "AL"}, {"id": 405395, "rank": 30, "value": "177", "league": "NL"}, {"id": 407893, "rank": 30, "value": "177", "league": "AL"}]