[{"id": 400085, "rank": 1, "value": "214", "league": "AL"}, {"id": 429664, "rank": 2, "value": "200", "league": "AL"}, {"id": 471865, "rank": 3, "value": "197", "league": "NL"}, {"id": 134181, "rank": 4, "value": "189", "league": "AL"}, {"id": 456714, "rank": 4, "value": "189", "league": "AL"}, {"id": 460075, "rank": 6, "value": "188", "league": "NL"}, {"id": 455976, "rank": 7, "value": "187", "league": "AL"}, {"id": 285078, "rank": 8, "value": "186", "league": "AL"}, {"id": 407812, "rank": 8, "value": "186", "league": "NL"}, {"id": 276545, "rank": 8, "value": "186", "league": "AL"}, {"id": 408307, "rank": 11, "value": "184", "league": "AL"}, {"id": 445988, "rank": 11, "value": "184", "league": "NL"}, {"id": 405395, "rank": 13, "value": "183", "league": "NL"}, {"id": 457706, "rank": 14, "value": "181", "league": "AL"}, {"id": 408234, "rank": 15, "value": "180", "league": "AL"}, {"id": 116539, "rank": 16, "value": "179", "league": "AL"}, {"id": 334393, "rank": 16, "value": "179", "league": "AL"}, {"id": 115223, "rank": 18, "value": "178", "league": "AL"}, {"id": 458015, "rank": 19, "value": "177", "league": "NL"}, {"id": 408236, "rank": 20, "value": "176", "league": "NL"}, {"id": 430001, "rank": 21, "value": "175", "league": "NL"}, {"id": 431171, "rank": 22, "value": "174", "league": "NL"}, {"id": 340192, "rank": 22, "value": "174", "league": "AL"}, {"id": 452254, "rank": 24, "value": "173", "league": "NL"}, {"id": 435062, "rank": 25, "value": "172", "league": "AL"}, {"id": 408252, "rank": 25, "value": "172", "league": "NL"}, {"id": 117244, "rank": 27, "value": "171", "league": "AL"}, {"id": 123173, "rank": 27, "value": "171", "league": "NL"}, {"id": 407781, "rank": 29, "value": "170", "league": "NL"}, {"id": 430321, "rank": 29, "value": "170", "league": "AL"}]