[{"id": 547180, "rank": 1, "value": ".460", "league": "NL"}, {"id": 458015, "rank": 2, "value": ".459", "league": "NL"}, {"id": 408234, "rank": 3, "value": ".440", "league": "AL"}, {"id": 502671, "rank": 4, "value": ".435", "league": "NL"}, {"id": 545361, "rank": 5, "value": ".402", "league": "AL"}, {"id": 457705, "rank": 6, "value": ".401", "league": "NL"}, {"id": 519203, "rank": 7, "value": ".387", "league": "NL"}, {"id": 488726, "rank": 8, "value": ".379", "league": "AL"}, {"id": 457763, "rank": 9, "value": ".379", "league": "NL"}, {"id": 425902, "rank": 10, "value": ".378", "league": "AL"}, {"id": 430832, "rank": 11, "value": ".377", "league": "AL"}, {"id": 425783, "rank": 12, "value": ".375", "league": "AL"}, {"id": 488862, "rank": 13, "value": ".375", "league": "NL"}, {"id": 543401, "rank": 14, "value": ".372", "league": "AL"}, {"id": 429665, "rank": 15, "value": ".372", "league": "AL"}, {"id": 444482, "rank": 16, "value": ".371", "league": "NL"}, {"id": 518626, "rank": 17, "value": ".371", "league": "AL"}, {"id": 455976, "rank": 18, "value": ".370", "league": "NL"}, {"id": 465041, "rank": 19, "value": ".370", "league": "NL"}, {"id": 443558, "rank": 20, "value": ".369", "league": "AL"}, {"id": 592178, "rank": 21, "value": ".369", "league": "NL"}, {"id": 572041, "rank": 22, "value": ".367", "league": "NL"}, {"id": 592885, "rank": 23, "value": ".366", "league": "NL"}, {"id": 572761, "rank": 24, "value": ".365", "league": "NL"}, {"id": 434158, "rank": 25, "value": ".364", "league": "NL"}, {"id": 543333, "rank": 26, "value": ".363", "league": "AL"}, {"id": 434778, "rank": 27, "value": ".362", "league": "AL"}, {"id": 448801, "rank": 28, "value": ".361", "league": "AL"}, {"id": 594809, "rank": 29, "value": ".361", "league": "AL"}, {"id": 456715, "rank": 30, "value": ".361", "league": "AL"}]