[{"id": 542340, "rank": 1, "value": "62", "league": "NL"}, {"id": 571740, "rank": 2, "value": "58", "league": "NL"}, {"id": 516782, "rank": 3, "value": "47", "league": "NL"}, {"id": 434658, "rank": 4, "value": "43", "league": "AL"}, {"id": 456488, "rank": 5, "value": "40", "league": "NL"}, {"id": 541650, "rank": 6, "value": "34", "league": "NL"}, {"id": 516416, "rank": 7, "value": "33", "league": "NL"}, {"id": 607208, "rank": 7, "value": "33", "league": "NL"}, {"id": 502671, "rank": 9, "value": "32", "league": "NL"}, {"id": 514888, "rank": 10, "value": "30", "league": "AL"}, {"id": 502481, "rank": 10, "value": "30", "league": "AL"}, {"id": 608671, "rank": 10, "value": "30", "league": "NL"}, {"id": 543829, "rank": 10, "value": "30", "league": "NL"}, {"id": 545361, "rank": 10, "value": "30", "league": "AL"}, {"id": 571976, "rank": 15, "value": "28", "league": "NL"}, {"id": 425834, "rank": 16, "value": "27", "league": "AL"}, {"id": 605141, "rank": 17, "value": "26", "league": "AL"}, {"id": 546318, "rank": 18, "value": "25", "league": "NL"}, {"id": 462101, "rank": 19, "value": "24", "league": "AL"}, {"id": 547982, "rank": 19, "value": "24", "league": "AL"}, {"id": 542979, "rank": 21, "value": "23", "league": "NL"}, {"id": 608070, "rank": 22, "value": "22", "league": "AL"}, {"id": 435622, "rank": 23, "value": "21", "league": "AL"}, {"id": 547180, "rank": 23, "value": "21", "league": "NL"}, {"id": 595281, "rank": 23, "value": "21", "league": "AL"}, {"id": 572008, "rank": 23, "value": "21", "league": "NL"}, {"id": 606299, "rank": 23, "value": "21", "league": "NL"}, {"id": 453056, "rank": 28, "value": "20", "league": "AL"}, {"id": 543281, "rank": 29, "value": "19", "league": "NL"}, {"id": 596019, "rank": 29, "value": "19", "league": "AL"}]