[{"id": 592885, "rank": 1, "value": "1.100", "league": "NL"}, {"id": 545361, "rank": 2, "value": "1.083", "league": "AL"}, {"id": 641355, "rank": 3, "value": "1.035", "league": "NL"}, {"id": 443558, "rank": 4, "value": "1.031", "league": "AL"}, {"id": 608324, "rank": 5, "value": "1.015", "league": "AL"}, {"id": 543685, "rank": 6, "value": "1.010", "league": "NL"}, {"id": 606466, "rank": 7, "value": ".981", "league": "NL"}, {"id": 543807, "rank": 8, "value": ".974", "league": "AL"}, {"id": 571448, "rank": 9, "value": ".962", "league": "NL"}, {"id": 665742, "rank": 10, "value": ".949", "league": "NL"}, {"id": 624413, "rank": 11, "value": ".941", "league": "NL"}, {"id": 453568, "rank": 12, "value": ".940", "league": "NL"}, {"id": 502110, "rank": 12, "value": ".940", "league": "AL"}, {"id": 593428, "rank": 14, "value": ".939", "league": "AL"}, {"id": 518692, "rank": 15, "value": ".938", "league": "NL"}, {"id": 605137, "rank": 16, "value": ".936", "league": "NL"}, {"id": 553993, "rank": 17, "value": ".930", "league": "NL"}, {"id": 519203, "rank": 18, "value": ".925", "league": "NL"}, {"id": 624585, "rank": 19, "value": ".923", "league": "AL"}, {"id": 640457, "rank": 20, "value": ".922", "league": "AL"}, {"id": 596115, "rank": 21, "value": ".917", "league": "NL"}, {"id": 646240, "rank": 22, "value": ".916", "league": "AL"}, {"id": 605141, "rank": 23, "value": ".915", "league": "AL"}, {"id": 643446, "rank": 23, "value": ".915", "league": "NL"}, {"id": 660162, "rank": 23, "value": ".915", "league": "AL"}, {"id": 467793, "rank": 26, "value": ".912", "league": "AL"}, {"id": 514888, "rank": 27, "value": ".903", "league": "AL"}, {"id": 592178, "rank": 27, "value": ".903", "league": "NL"}, {"id": 518626, "rank": 29, "value": ".900", "league": "NL"}, {"id": 641820, "rank": 30, "value": ".899", "league": "AL"}]