{
  "key": "nomo",
  "name_jp": "野茂英雄",
  "name_en": "Hideo Nomo",
  "team_jp": "ロサンゼルス・ドジャース",
  "team_en": "Los Angeles Dodgers",
  "team_short": "LAD",
  "league": "NL",
  "level": "FORMER",
  "type": "pitcher",
  "position_jp": "先発投手",
  "position_en": "Starting Pitcher",
  "mlb_years": "1995-2008",
  "current_status_jp": "2008年引退",
  "current_status_en": "Retired (2008)",
  "basic": {
    "pitching": {
      "w": 123,
      "l": 109,
      "era": "4.24",
      "so": 1918,
      "ip": "1976.1",
      "whip": "1.35",
      "sv": 0,
      "hld": 0
    }
  },
  "yearly": [
    {
      "year": 1995,
      "team": "LA",
      "type": "pit",
      "w": 13,
      "l": 6,
      "era": "2.54",
      "so": 236,
      "ip": "191.1",
      "whip": "1.06",
      "sv": 0,
      "hld": 0,
      "led": [
        "so"
      ],
      "top10": [
        "era",
        "whip"
      ]
    },
    {
      "year": 1996,
      "team": "LA",
      "type": "pit",
      "w": 16,
      "l": 11,
      "era": "3.19",
      "so": 234,
      "ip": "228.1",
      "whip": "1.16",
      "sv": 0,
      "hld": 0,
      "top10": [
        "era",
        "w",
        "so",
        "whip"
      ]
    },
    {
      "year": 1997,
      "team": "LA",
      "type": "pit",
      "w": 14,
      "l": 12,
      "era": "4.25",
      "so": 233,
      "ip": "207.1",
      "whip": "1.37",
      "sv": 0,
      "hld": 0,
      "top10": [
        "so"
      ]
    },
    {
      "year": 1998,
      "team": "LA/NYM",
      "type": "pit",
      "w": 6,
      "l": 12,
      "era": "4.92",
      "so": 167,
      "ip": "157.1",
      "whip": "1.42",
      "sv": 0,
      "hld": 0
    },
    {
      "year": 1999,
      "team": "MIL",
      "type": "pit",
      "w": 12,
      "l": 8,
      "era": "4.54",
      "so": 161,
      "ip": "176.1",
      "whip": "1.42",
      "sv": 0,
      "hld": 0
    },
    {
      "year": 2000,
      "team": "DET",
      "type": "pit",
      "w": 8,
      "l": 12,
      "era": "4.74",
      "so": 181,
      "ip": "190.0",
      "whip": "1.47",
      "sv": 0,
      "hld": 0
    },
    {
      "year": 2001,
      "team": "BOS",
      "type": "pit",
      "w": 13,
      "l": 10,
      "era": "4.50",
      "so": 220,
      "ip": "198.0",
      "whip": "1.35",
      "sv": 0,
      "hld": 0,
      "led": [
        "so"
      ]
    },
    {
      "year": 2002,
      "team": "LA",
      "type": "pit",
      "w": 16,
      "l": 6,
      "era": "3.39",
      "so": 193,
      "ip": "220.1",
      "whip": "1.32",
      "sv": 0,
      "hld": 0,
      "top10": [
        "so"
      ]
    },
    {
      "year": 2003,
      "team": "LA",
      "type": "pit",
      "w": 16,
      "l": 13,
      "era": "3.09",
      "so": 177,
      "ip": "218.1",
      "whip": "1.25",
      "sv": 0,
      "hld": 0,
      "top10": [
        "era"
      ]
    },
    {
      "year": 2004,
      "team": "LA",
      "type": "pit",
      "w": 4,
      "l": 11,
      "era": "8.25",
      "so": 54,
      "ip": "84.0",
      "whip": "1.75",
      "sv": 0,
      "hld": 0
    },
    {
      "year": 2005,
      "team": "TB",
      "type": "pit",
      "w": 5,
      "l": 8,
      "era": "7.24",
      "so": 59,
      "ip": "100.2",
      "whip": "1.77",
      "sv": 0,
      "hld": 0
    },
    {
      "year": 2008,
      "team": "KC",
      "type": "pit",
      "w": 0,
      "l": 0,
      "era": "18.69",
      "so": 3,
      "ip": "4.1",
      "whip": "3.23",
      "sv": 0,
      "hld": 0
    }
  ],
  "updated_at": "2026-04-25",
  "awards": [
    {
      "year": 1995,
      "label": "オールスター",
      "cat": "as",
      "raw": "NL All-Star"
    },
    {
      "year": 1995,
      "label": "新人王",
      "cat": "roy",
      "raw": "Jackie Robinson NL Rookie of the Year"
    }
  ],
  "basic_season": {
    "pitching": "career"
  },
  "legend": true,
  "splits_lr_career": {
    "pitching": {
      "vs_left": {
        "ab": 3524,
        "ba": ".235",
        "hr": 107,
        "k": 936,
        "bb": 444,
        "ops": ".702",
        "obp": ".323",
        "slg": ".379"
      },
      "vs_right": {
        "ab": 3846,
        "ba": ".244",
        "hr": 144,
        "k": 982,
        "bb": 464,
        "ops": ".741",
        "obp": ".326",
        "slg": ".415"
      }
    }
  }
}