{
  "key": "suzuki",
  "name_jp": "鈴木誠也",
  "name_en": "Seiya Suzuki",
  "team_jp": "シカゴ・カブス",
  "team_en": "Chicago Cubs",
  "team_short": "CHC",
  "league": "NL",
  "level": "MLB",
  "type": "batter",
  "position_jp": "右翼手",
  "position_en": "Right Fielder",
  "basic": {
    "hitting": {
      "avg": ".321",
      "h": 26,
      "hr": 6,
      "rbi": 13,
      "sb": 0,
      "obp": ".417",
      "slg": ".568",
      "ops": ".985"
    }
  },
  "savant": {
    "hitting": {
      "exit_velocity_avg": 90.5,
      "launch_angle_avg": 13.2,
      "barrel_batted_rate": 11.8,
      "hard_hit_percent": 47.3,
      "xba": ".270",
      "xslg": ".470",
      "xwoba": ".355",
      "k_percent": 22.1,
      "bb_percent": 9.2
    }
  },
  "yearly": [
    {
      "year": 2022,
      "team": "CHC",
      "type": "hit",
      "avg": ".262",
      "h": 104,
      "hr": 14,
      "rbi": 46,
      "sb": 9,
      "obp": ".336",
      "slg": ".433",
      "ops": ".769"
    },
    {
      "year": 2023,
      "team": "CHC",
      "type": "hit",
      "avg": ".285",
      "h": 147,
      "hr": 20,
      "rbi": 74,
      "sb": 6,
      "obp": ".357",
      "slg": ".485",
      "ops": ".842"
    },
    {
      "year": 2024,
      "team": "CHC",
      "type": "hit",
      "avg": ".283",
      "h": 145,
      "hr": 21,
      "rbi": 73,
      "sb": 16,
      "obp": ".366",
      "slg": ".482",
      "ops": ".848"
    },
    {
      "year": 2025,
      "team": "CHC",
      "type": "hit",
      "avg": ".245",
      "h": 140,
      "hr": 32,
      "rbi": 103,
      "sb": 5,
      "obp": ".326",
      "slg": ".478",
      "ops": ".804"
    },
    {
      "year": 2026,
      "team": "CHC",
      "type": "hit",
      "avg": ".294",
      "h": 15,
      "hr": 3,
      "rbi": 7,
      "sb": 0,
      "obp": ".419",
      "slg": ".490",
      "ops": ".909"
    }
  ],
  "updated_at": "2026-05-05",
  "basic_season": {
    "hitting": 2026
  },
  "splits_lr_current": {
    "hitting": {
      "vs_left": {
        "ab": 23,
        "h": 8,
        "hr": 1,
        "rbi": 2,
        "sb": null,
        "avg": ".348",
        "obp": ".464",
        "slg": ".522",
        "ops": ".986"
      },
      "vs_right": {
        "ab": 58,
        "h": 18,
        "hr": 5,
        "rbi": 11,
        "sb": null,
        "avg": ".310",
        "obp": ".397",
        "slg": ".586",
        "ops": ".983"
      }
    }
  },
  "splits_lr_current_season": 2026,
  "splits_lr_career": {
    "hitting": {
      "vs_left": {
        "ab": 540,
        "h": 148,
        "hr": 22,
        "rbi": 78,
        "sb": null,
        "avg": ".274",
        "obp": ".373",
        "slg": ".474",
        "ops": ".847"
      },
      "vs_right": {
        "ab": 1536,
        "h": 414,
        "hr": 71,
        "rbi": 231,
        "sb": null,
        "avg": ".270",
        "obp": ".340",
        "slg": ".477",
        "ops": ".817"
      }
    }
  },
  "bio_jp": "広角に長打を打てる外野手。2023年に20HR/74打点/.842 OPSでブレイク。",
  "bio_en": "Power-to-all-fields outfielder. Breakout 2023 with 20 HR / 74 RBI / .842 OPS."
}