{"vs_left": {"gamesPlayed": 24, "groundOuts": 9, "airOuts": 10, "doubles": 2, "triples": 0, "homeRuns": 3, "strikeOuts": 7, "baseOnBalls": 6, "intentionalWalks": 1, "hits": 12, "hitByPitch": 2, "avg": ".316", "atBats": 38, "obp": ".435", "slg": ".605", "ops": "1.040", "groundIntoDoublePlay": 1, "groundIntoTriplePlay": 0, "numberOfPitches": 170, "plateAppearances": 46, "totalBases": 23, "rbi": 3, "leftOnBase": 17, "sacBunts": 0, "sacFlies": 0, "babip": ".321", "groundOutsToAirouts": "0.90", "catchersInterference": 0, "atBatsPerHomeRun": "12.67"}, "vs_right": {"gamesPlayed": 31, "groundOuts": 20, "airOuts": 22, "doubles": 4, "triples": 0, "homeRuns": 3, "strikeOuts": 29, "baseOnBalls": 20, "intentionalWalks": 5, "hits": 18, "hitByPitch": 2, "avg": ".207", "atBats": 87, "obp": ".360", "slg": ".356", "ops": ".716", "groundIntoDoublePlay": 2, "groundIntoTriplePlay": 0, "numberOfPitches": 430, "plateAppearances": 112, "totalBases": 31, "rbi": 11, "leftOnBase": 39, "sacBunts": 0, "sacFlies": 2, "babip": ".263", "groundOutsToAirouts": "0.91", "catchersInterference": 1, "atBatsPerHomeRun": "29.00"}}