{"vs_left": {"gamesPlayed": 30, "groundOuts": 4, "airOuts": 9, "doubles": 1, "triples": 0, "homeRuns": 4, "strikeOuts": 22, "baseOnBalls": 9, "intentionalWalks": 1, "hits": 10, "hitByPitch": 0, "avg": ".227", "atBats": 44, "obp": ".352", "slg": ".523", "ops": ".875", "groundIntoDoublePlay": 0, "groundIntoTriplePlay": 0, "numberOfPitches": 245, "plateAppearances": 54, "totalBases": 23, "rbi": 9, "leftOnBase": 22, "sacBunts": 0, "sacFlies": 1, "babip": ".316", "groundOutsToAirouts": "0.44", "catchersInterference": 0, "atBatsPerHomeRun": "11.00"}, "vs_right": {"gamesPlayed": 40, "groundOuts": 18, "airOuts": 19, "doubles": 0, "triples": 0, "homeRuns": 11, "strikeOuts": 41, "baseOnBalls": 22, "intentionalWalks": 3, "hits": 23, "hitByPitch": 0, "avg": ".228", "atBats": 101, "obp": ".366", "slg": ".554", "ops": ".920", "groundIntoDoublePlay": 1, "groundIntoTriplePlay": 0, "numberOfPitches": 518, "plateAppearances": 123, "totalBases": 56, "rbi": 20, "leftOnBase": 35, "sacBunts": 0, "sacFlies": 0, "babip": ".245", "groundOutsToAirouts": "0.95", "catchersInterference": 0, "atBatsPerHomeRun": "9.18"}}